README.rst
setup.py
pyAltmetric.egg-info/PKG-INFO
pyAltmetric.egg-info/SOURCES.txt
pyAltmetric.egg-info/dependency_links.txt
pyAltmetric.egg-info/requires.txt
pyAltmetric.egg-info/top_level.txt
pyaltmetric/__init__.py
pyaltmetric/pyaltmetric.py
pyaltmetric.egg-info/SOURCES.txt