Metadata-Version: 1.0
Name: pyaltmetric
Version: 0.1.1
Summary: Python Altmetric API v1 wrapper
Home-page: https://github.com/wearp/pyaltmetric
Author: Will Earp
Author-email: will.earp@icloud.com
License: BSD
Keywords: Altmetric altmetrics api wrapper
Platform: UNKNOWN
